aioqvapay/__init__.py
aioqvapay/v1/__init__.py
aioqvapay/v1/auth.py
aioqvapay/v1/client.py
aioqvapay/v1/exceptions.py
aioqvapay/v1/models/__init__.py
aioqvapay/v1/models/info_model.py
aioqvapay/v1/models/invoice_model.py
aioqvapay/v1/models/owner_model.py
aioqvapay/v1/models/paginated_transactions_model.py
aioqvapay/v1/models/paid_by_model.py
aioqvapay/v1/models/transaction_detail_model.py
aioqvapay/v1/models/transaction_model.py
aioqvapay/v1/utils.py
aioqvapay/v2/__init__.py
aioqvapay/v2/auth.py
aioqvapay/v2/client.py
aioqvapay/v2/exceptions.py
aioqvapay/v2/models/__init__.py
aioqvapay/v2/models/info_model.py
aioqvapay/v2/models/invoice_model.py
aioqvapay/v2/models/owner_model.py
aioqvapay/v2/models/paginated_transactions_model.py
aioqvapay/v2/models/paid_by_model.py
aioqvapay/v2/models/transaction_detail_model.py
aioqvapay/v2/models/transaction_model.py
aioqvapay/v2/utils.py
aioqvapay-0.3.4.dist-info/LICENSE
aioqvapay-0.3.4.dist-info/WHEEL
aioqvapay-0.3.4.dist-info/METADATA
aioqvapay-0.3.4.dist-info/RECORD
