Metadata-Version: 2.1
Name: aioqvapay
Version: 0.3.4
Summary: Asynchronous and also synchronous non-official QvaPay client for asyncio and Python language.
Home-page: https://leynier.github.io/aioqvapay
License: MIT
Author: Leynier Gutiérrez González
Author-email: leynier41@gmail.com
Requires-Python: >=3.6.14,<4.0.0
Classifier: License :: OSI Approved :: MIT License
Classifier: Programming Language :: Python :: 3
Classifier: Programming Language :: Python :: 3.7
Classifier: Programming Language :: Python :: 3.8
Classifier: Programming Language :: Python :: 3.9
Requires-Dist: httpx[brotli] (>=0.19.0,<0.20.0)
Requires-Dist: pydantic[dotenv] (>=1.8.2,<2.0.0)
Project-URL: Documentation, https://leynier.github.io/aioqvapay
Project-URL: Repository, https://github.com/leynier/aioqvapay
